[
  {
    "issueNumber": "20260422100051660",
    "number": "1",
    "color": "green",
    "premium": "1",
    "sum": 0
  },
  {
    "issueNumber": "20260422100051659",
    "number": "1",
    "color": "green",
    "premium": "1",
    "sum": 0
  },
  {
    "issueNumber": "20260422100051658",
    "number": "2",
    "color": "red",
    "premium": "2",
    "sum": 0
  },
  {
    "issueNumber": "20260422100051657",
    "number": "8",
    "color": "red",
    "premium": "8",
    "sum": 0
  },
  {
    "issueNumber": "20260422100051656",
    "number": "1",
    "color": "green",
    "premium": "1",
    "sum": 0
  },
  {
    "issueNumber": "20260422100051655",
    "number": "7",
    "color": "green",
    "premium": "7",
    "sum": 0
  },
  {
    "issueNumber": "20260422100051654",
    "number": "0",
    "color": "red,violet",
    "premium": "0",
    "sum": 0
  },
  {
    "issueNumber": "20260422100051653",
    "number": "8",
    "color": "red",
    "premium": "8",
    "sum": 0
  },
  {
    "issueNumber": "20260422100051652",
    "number": "8",
    "color": "red",
    "premium": "8",
    "sum": 0
  },
  {
    "issueNumber": "20260422100051651",
    "number": "6",
    "color": "red",
    "premium": "6",
    "sum": 0
  },
  {
    "issueNumber": "20260422100051650",
    "number": "9",
    "color": "green",
    "premium": "9",
    "sum": 0
  },
  {
    "issueNumber": "20260422100051649",
    "number": "5",
    "color": "green,violet",
    "premium": "5",
    "sum": 0
  },
  {
    "issueNumber": "20260422100051648",
    "number": "4",
    "color": "red",
    "premium": "4",
    "sum": 0
  },
  {
    "issueNumber": "20260422100051647",
    "number": "0",
    "color": "red,violet",
    "premium": "0",
    "sum": 0
  },
  {
    "issueNumber": "20260422100051646",
    "number": "7",
    "color": "green",
    "premium": "7",
    "sum": 0
  },
  {
    "issueNumber": "20260422100051645",
    "number": "8",
    "color": "red",
    "premium": "8",
    "sum": 0
  },
  {
    "issueNumber": "20260422100051644",
    "number": "7",
    "color": "green",
    "premium": "7",
    "sum": 0
  },
  {
    "issueNumber": "20260422100051643",
    "number": "1",
    "color": "green",
    "premium": "1",
    "sum": 0
  },
  {
    "issueNumber": "20260422100051642",
    "number": "7",
    "color": "green",
    "premium": "7",
    "sum": 0
  },
  {
    "issueNumber": "20260422100051641",
    "number": "9",
    "color": "green",
    "premium": "9",
    "sum": 0
  },
  {
    "issueNumber": "20260422100051640",
    "number": "4",
    "color": "red",
    "premium": "4",
    "sum": 0
  },
  {
    "issueNumber": "20260422100051639",
    "number": "8",
    "color": "red",
    "premium": "8",
    "sum": 0
  },
  {
    "issueNumber": "20260422100051638",
    "number": "1",
    "color": "green",
    "premium": "1",
    "sum": 0
  },
  {
    "issueNumber": "20260422100051637",
    "number": "5",
    "color": "green,violet",
    "premium": "5",
    "sum": 0
  },
  {
    "issueNumber": "20260422100051636",
    "number": "7",
    "color": "green",
    "premium": "7",
    "sum": 0
  },
  {
    "issueNumber": "20260422100051635",
    "number": "9",
    "color": "green",
    "premium": "9",
    "sum": 0
  },
  {
    "issueNumber": "20260422100051634",
    "number": "3",
    "color": "green",
    "premium": "3",
    "sum": 0
  },
  {
    "issueNumber": "20260422100051633",
    "number": "8",
    "color": "red",
    "premium": "8",
    "sum": 0
  },
  {
    "issueNumber": "20260422100051632",
    "number": "4",
    "color": "red",
    "premium": "4",
    "sum": 0
  },
  {
    "issueNumber": "20260422100051631",
    "number": "7",
    "color": "green",
    "premium": "7",
    "sum": 0
  },
  {
    "issueNumber": "20260422100051630",
    "number": "3",
    "color": "green",
    "premium": "3",
    "sum": 0
  },
  {
    "issueNumber": "20260422100051629",
    "number": "8",
    "color": "red",
    "premium": "8",
    "sum": 0
  },
  {
    "issueNumber": "20260422100051628",
    "number": "6",
    "color": "red",
    "premium": "6",
    "sum": 0
  },
  {
    "issueNumber": "20260422100051627",
    "number": "0",
    "color": "red,violet",
    "premium": "0",
    "sum": 0
  },
  {
    "issueNumber": "20260422100051626",
    "number": "5",
    "color": "green,violet",
    "premium": "5",
    "sum": 0
  },
  {
    "issueNumber": "20260422100051625",
    "number": "2",
    "color": "red",
    "premium": "2",
    "sum": 0
  },
  {
    "issueNumber": "20260422100051624",
    "number": "1",
    "color": "green",
    "premium": "1",
    "sum": 0
  },
  {
    "issueNumber": "20260422100051623",
    "number": "0",
    "color": "red,violet",
    "premium": "0",
    "sum": 0
  },
  {
    "issueNumber": "20260422100051622",
    "number": "1",
    "color": "green",
    "premium": "1",
    "sum": 0
  },
  {
    "issueNumber": "20260422100051621",
    "number": "0",
    "color": "red,violet",
    "premium": "0",
    "sum": 0
  },
  {
    "issueNumber": "20260422100051620",
    "number": "3",
    "color": "green",
    "premium": "3",
    "sum": 0
  },
  {
    "issueNumber": "20260422100051619",
    "number": "8",
    "color": "red",
    "premium": "8",
    "sum": 0
  },
  {
    "issueNumber": "20260422100051618",
    "number": "3",
    "color": "green",
    "premium": "3",
    "sum": 0
  },
  {
    "issueNumber": "20260422100051617",
    "number": "1",
    "color": "green",
    "premium": "1",
    "sum": 0
  },
  {
    "issueNumber": "20260422100051616",
    "number": "5",
    "color": "green,violet",
    "premium": "5",
    "sum": 0
  },
  {
    "issueNumber": "20260422100051615",
    "number": "5",
    "color": "green,violet",
    "premium": "5",
    "sum": 0
  },
  {
    "issueNumber": "20260422100051614",
    "number": "1",
    "color": "green",
    "premium": "1",
    "sum": 0
  },
  {
    "issueNumber": "20260422100051613",
    "number": "6",
    "color": "red",
    "premium": "6",
    "sum": 0
  },
  {
    "issueNumber": "20260422100051612",
    "number": "4",
    "color": "red",
    "premium": "4",
    "sum": 0
  },
  {
    "issueNumber": "20260422100051611",
    "number": "0",
    "color": "red,violet",
    "premium": "0",
    "sum": 0
  },
  {
    "issueNumber": "20260422100051610",
    "number": "3",
    "color": "green",
    "premium": "3",
    "sum": 0
  },
  {
    "issueNumber": "20260422100051609",
    "number": "3",
    "color": "green",
    "premium": "3",
    "sum": 0
  },
  {
    "issueNumber": "20260422100051608",
    "number": "8",
    "color": "red",
    "premium": "8",
    "sum": 0
  },
  {
    "issueNumber": "20260422100051607",
    "number": "8",
    "color": "red",
    "premium": "8",
    "sum": 0
  },
  {
    "issueNumber": "20260422100051606",
    "number": "0",
    "color": "red,violet",
    "premium": "0",
    "sum": 0
  },
  {
    "issueNumber": "20260422100051605",
    "number": "7",
    "color": "green",
    "premium": "7",
    "sum": 0
  }
]