[
  {
    "issueNumber": "20260502100051164",
    "number": "6",
    "color": "red",
    "premium": "6",
    "sum": 0
  },
  {
    "issueNumber": "20260502100051163",
    "number": "0",
    "color": "red,violet",
    "premium": "0",
    "sum": 0
  },
  {
    "issueNumber": "20260502100051162",
    "number": "8",
    "color": "red",
    "premium": "8",
    "sum": 0
  },
  {
    "issueNumber": "20260502100051161",
    "number": "3",
    "color": "green",
    "premium": "3",
    "sum": 0
  },
  {
    "issueNumber": "20260502100051160",
    "number": "2",
    "color": "red",
    "premium": "2",
    "sum": 0
  },
  {
    "issueNumber": "20260502100051159",
    "number": "9",
    "color": "green",
    "premium": "9",
    "sum": 0
  },
  {
    "issueNumber": "20260502100051158",
    "number": "9",
    "color": "green",
    "premium": "9",
    "sum": 0
  },
  {
    "issueNumber": "20260502100051157",
    "number": "4",
    "color": "red",
    "premium": "4",
    "sum": 0
  },
  {
    "issueNumber": "20260502100051156",
    "number": "8",
    "color": "red",
    "premium": "8",
    "sum": 0
  },
  {
    "issueNumber": "20260502100051155",
    "number": "8",
    "color": "red",
    "premium": "8",
    "sum": 0
  },
  {
    "issueNumber": "20260502100051154",
    "number": "8",
    "color": "red",
    "premium": "8",
    "sum": 0
  },
  {
    "issueNumber": "20260502100051153",
    "number": "9",
    "color": "green",
    "premium": "9",
    "sum": 0
  },
  {
    "issueNumber": "20260502100051152",
    "number": "1",
    "color": "green",
    "premium": "1",
    "sum": 0
  },
  {
    "issueNumber": "20260502100051151",
    "number": "7",
    "color": "green",
    "premium": "7",
    "sum": 0
  }
]