[
  {
    "issueNumber": "20260515100050422",
    "number": "5",
    "color": "green,violet",
    "premium": "5",
    "sum": 0
  },
  {
    "issueNumber": "20260515100050421",
    "number": "2",
    "color": "red",
    "premium": "2",
    "sum": 0
  },
  {
    "issueNumber": "20260515100050420",
    "number": "3",
    "color": "green",
    "premium": "3",
    "sum": 0
  },
  {
    "issueNumber": "20260515100050419",
    "number": "1",
    "color": "green",
    "premium": "1",
    "sum": 0
  },
  {
    "issueNumber": "20260515100050418",
    "number": "5",
    "color": "green,violet",
    "premium": "5",
    "sum": 0
  },
  {
    "issueNumber": "20260515100050417",
    "number": "5",
    "color": "green,violet",
    "premium": "5",
    "sum": 0
  },
  {
    "issueNumber": "20260515100050416",
    "number": "4",
    "color": "red",
    "premium": "4",
    "sum": 0
  },
  {
    "issueNumber": "20260515100050415",
    "number": "0",
    "color": "red,violet",
    "premium": "0",
    "sum": 0
  },
  {
    "issueNumber": "20260515100050414",
    "number": "6",
    "color": "red",
    "premium": "6",
    "sum": 0
  },
  {
    "issueNumber": "20260515100050413",
    "number": "8",
    "color": "red",
    "premium": "8",
    "sum": 0
  },
  {
    "issueNumber": "20260515100050412",
    "number": "6",
    "color": "red",
    "premium": "6",
    "sum": 0
  },
  {
    "issueNumber": "20260515100050411",
    "number": "7",
    "color": "green",
    "premium": "7",
    "sum": 0
  },
  {
    "issueNumber": "20260515100050410",
    "number": "8",
    "color": "red",
    "premium": "8",
    "sum": 0
  },
  {
    "issueNumber": "20260515100050409",
    "number": "5",
    "color": "green,violet",
    "premium": "5",
    "sum": 0
  },
  {
    "issueNumber": "20260515100050408",
    "number": "5",
    "color": "green,violet",
    "premium": "5",
    "sum": 0
  },
  {
    "issueNumber": "20260515100050407",
    "number": "3",
    "color": "green",
    "premium": "3",
    "sum": 0
  },
  {
    "issueNumber": "20260515100050406",
    "number": "4",
    "color": "red",
    "premium": "4",
    "sum": 0
  },
  {
    "issueNumber": "20260515100050405",
    "number": "2",
    "color": "red",
    "premium": "2",
    "sum": 0
  },
  {
    "issueNumber": "20260515100050404",
    "number": "3",
    "color": "green",
    "premium": "3",
    "sum": 0
  },
  {
    "issueNumber": "20260515100050403",
    "number": "0",
    "color": "red,violet",
    "premium": "0",
    "sum": 0
  },
  {
    "issueNumber": "20260515100050402",
    "number": "6",
    "color": "red",
    "premium": "6",
    "sum": 0
  },
  {
    "issueNumber": "20260515100050401",
    "number": "7",
    "color": "green",
    "premium": "7",
    "sum": 0
  },
  {
    "issueNumber": "20260515100050400",
    "number": "2",
    "color": "red",
    "premium": "2",
    "sum": 0
  },
  {
    "issueNumber": "20260515100050399",
    "number": "4",
    "color": "red",
    "premium": "4",
    "sum": 0
  },
  {
    "issueNumber": "20260515100050398",
    "number": "2",
    "color": "red",
    "premium": "2",
    "sum": 0
  },
  {
    "issueNumber": "20260515100050397",
    "number": "8",
    "color": "red",
    "premium": "8",
    "sum": 0
  },
  {
    "issueNumber": "20260515100050396",
    "number": "0",
    "color": "red,violet",
    "premium": "0",
    "sum": 0
  },
  {
    "issueNumber": "20260515100050395",
    "number": "2",
    "color": "red",
    "premium": "2",
    "sum": 0
  },
  {
    "issueNumber": "20260515100050394",
    "number": "4",
    "color": "red",
    "premium": "4",
    "sum": 0
  },
  {
    "issueNumber": "20260515100050393",
    "number": "9",
    "color": "green",
    "premium": "9",
    "sum": 0
  },
  {
    "issueNumber": "20260515100050392",
    "number": "8",
    "color": "red",
    "premium": "8",
    "sum": 0
  },
  {
    "issueNumber": "20260515100050391",
    "number": "7",
    "color": "green",
    "premium": "7",
    "sum": 0
  },
  {
    "issueNumber": "20260515100050390",
    "number": "6",
    "color": "red",
    "premium": "6",
    "sum": 0
  },
  {
    "issueNumber": "20260515100050389",
    "number": "2",
    "color": "red",
    "premium": "2",
    "sum": 0
  },
  {
    "issueNumber": "20260515100050388",
    "number": "5",
    "color": "green,violet",
    "premium": "5",
    "sum": 0
  },
  {
    "issueNumber": "20260515100050387",
    "number": "0",
    "color": "red,violet",
    "premium": "0",
    "sum": 0
  },
  {
    "issueNumber": "20260515100050386",
    "number": "6",
    "color": "red",
    "premium": "6",
    "sum": 0
  },
  {
    "issueNumber": "20260515100050385",
    "number": "8",
    "color": "red",
    "premium": "8",
    "sum": 0
  },
  {
    "issueNumber": "20260515100050384",
    "number": "3",
    "color": "green",
    "premium": "3",
    "sum": 0
  },
  {
    "issueNumber": "20260515100050383",
    "number": "0",
    "color": "red,violet",
    "premium": "0",
    "sum": 0
  },
  {
    "issueNumber": "20260515100050382",
    "number": "0",
    "color": "red,violet",
    "premium": "0",
    "sum": 0
  },
  {
    "issueNumber": "20260515100050381",
    "number": "8",
    "color": "red",
    "premium": "8",
    "sum": 0
  },
  {
    "issueNumber": "20260515100050380",
    "number": "5",
    "color": "green,violet",
    "premium": "5",
    "sum": 0
  },
  {
    "issueNumber": "20260515100050379",
    "number": "2",
    "color": "red",
    "premium": "2",
    "sum": 0
  },
  {
    "issueNumber": "20260515100050378",
    "number": "1",
    "color": "green",
    "premium": "1",
    "sum": 0
  },
  {
    "issueNumber": "20260515100050377",
    "number": "1",
    "color": "green",
    "premium": "1",
    "sum": 0
  },
  {
    "issueNumber": "20260515100050376",
    "number": "5",
    "color": "green,violet",
    "premium": "5",
    "sum": 0
  },
  {
    "issueNumber": "20260515100050375",
    "number": "9",
    "color": "green",
    "premium": "9",
    "sum": 0
  },
  {
    "issueNumber": "20260515100050374",
    "number": "9",
    "color": "green",
    "premium": "9",
    "sum": 0
  },
  {
    "issueNumber": "20260515100050373",
    "number": "5",
    "color": "green,violet",
    "premium": "5",
    "sum": 0
  },
  {
    "issueNumber": "20260515100050372",
    "number": "0",
    "color": "red,violet",
    "premium": "0",
    "sum": 0
  },
  {
    "issueNumber": "20260515100050371",
    "number": "6",
    "color": "red",
    "premium": "6",
    "sum": 0
  },
  {
    "issueNumber": "20260515100050370",
    "number": "4",
    "color": "red",
    "premium": "4",
    "sum": 0
  },
  {
    "issueNumber": "20260515100050369",
    "number": "3",
    "color": "green",
    "premium": "3",
    "sum": 0
  },
  {
    "issueNumber": "20260515100050368",
    "number": "0",
    "color": "red,violet",
    "premium": "0",
    "sum": 0
  },
  {
    "issueNumber": "20260515100050367",
    "number": "8",
    "color": "red",
    "premium": "8",
    "sum": 0
  },
  {
    "issueNumber": "20260515100050366",
    "number": "6",
    "color": "red",
    "premium": "6",
    "sum": 0
  },
  {
    "issueNumber": "20260515100050365",
    "number": "2",
    "color": "red",
    "premium": "2",
    "sum": 0
  },
  {
    "issueNumber": "20260515100050364",
    "number": "6",
    "color": "red",
    "premium": "6",
    "sum": 0
  },
  {
    "issueNumber": "20260515100050363",
    "number": "3",
    "color": "green",
    "premium": "3",
    "sum": 0
  },
  {
    "issueNumber": "20260515100050362",
    "number": "9",
    "color": "green",
    "premium": "9",
    "sum": 0
  },
  {
    "issueNumber": "20260515100050361",
    "number": "8",
    "color": "red",
    "premium": "8",
    "sum": 0
  },
  {
    "issueNumber": "20260515100050360",
    "number": "6",
    "color": "red",
    "premium": "6",
    "sum": 0
  },
  {
    "issueNumber": "20260515100050359",
    "number": "0",
    "color": "red,violet",
    "premium": "0",
    "sum": 0
  },
  {
    "issueNumber": "20260515100050358",
    "number": "9",
    "color": "green",
    "premium": "9",
    "sum": 0
  },
  {
    "issueNumber": "20260515100050357",
    "number": "9",
    "color": "green",
    "premium": "9",
    "sum": 0
  },
  {
    "issueNumber": "20260515100050356",
    "number": "6",
    "color": "red",
    "premium": "6",
    "sum": 0
  },
  {
    "issueNumber": "20260515100050355",
    "number": "4",
    "color": "red",
    "premium": "4",
    "sum": 0
  },
  {
    "issueNumber": "20260515100050354",
    "number": "2",
    "color": "red",
    "premium": "2",
    "sum": 0
  },
  {
    "issueNumber": "20260515100050353",
    "number": "9",
    "color": "green",
    "premium": "9",
    "sum": 0
  },
  {
    "issueNumber": "20260515100050352",
    "number": "5",
    "color": "green,violet",
    "premium": "5",
    "sum": 0
  },
  {
    "issueNumber": "20260515100050351",
    "number": "6",
    "color": "red",
    "premium": "6",
    "sum": 0
  },
  {
    "issueNumber": "20260515100050350",
    "number": "0",
    "color": "red,violet",
    "premium": "0",
    "sum": 0
  },
  {
    "issueNumber": "20260515100050349",
    "number": "8",
    "color": "red",
    "premium": "8",
    "sum": 0
  },
  {
    "issueNumber": "20260515100050348",
    "number": "7",
    "color": "green",
    "premium": "7",
    "sum": 0
  },
  {
    "issueNumber": "20260515100050347",
    "number": "2",
    "color": "red",
    "premium": "2",
    "sum": 0
  },
  {
    "issueNumber": "20260515100050346",
    "number": "9",
    "color": "green",
    "premium": "9",
    "sum": 0
  },
  {
    "issueNumber": "20260515100050345",
    "number": "0",
    "color": "red,violet",
    "premium": "0",
    "sum": 0
  },
  {
    "issueNumber": "20260515100050344",
    "number": "1",
    "color": "green",
    "premium": "1",
    "sum": 0
  },
  {
    "issueNumber": "20260515100050343",
    "number": "6",
    "color": "red",
    "premium": "6",
    "sum": 0
  },
  {
    "issueNumber": "20260515100050342",
    "number": "6",
    "color": "red",
    "premium": "6",
    "sum": 0
  },
  {
    "issueNumber": "20260515100050341",
    "number": "6",
    "color": "red",
    "premium": "6",
    "sum": 0
  },
  {
    "issueNumber": "20260515100050340",
    "number": "4",
    "color": "red",
    "premium": "4",
    "sum": 0
  },
  {
    "issueNumber": "20260515100050339",
    "number": "8",
    "color": "red",
    "premium": "8",
    "sum": 0
  },
  {
    "issueNumber": "20260515100050338",
    "number": "9",
    "color": "green",
    "premium": "9",
    "sum": 0
  },
  {
    "issueNumber": "20260515100050337",
    "number": "5",
    "color": "green,violet",
    "premium": "5",
    "sum": 0
  },
  {
    "issueNumber": "20260515100050336",
    "number": "0",
    "color": "red,violet",
    "premium": "0",
    "sum": 0
  },
  {
    "issueNumber": "20260515100050335",
    "number": "0",
    "color": "red,violet",
    "premium": "0",
    "sum": 0
  },
  {
    "issueNumber": "20260515100050334",
    "number": "8",
    "color": "red",
    "premium": "8",
    "sum": 0
  },
  {
    "issueNumber": "20260515100050333",
    "number": "6",
    "color": "red",
    "premium": "6",
    "sum": 0
  },
  {
    "issueNumber": "20260515100050332",
    "number": "9",
    "color": "green",
    "premium": "9",
    "sum": 0
  },
  {
    "issueNumber": "20260515100050331",
    "number": "5",
    "color": "green,violet",
    "premium": "5",
    "sum": 0
  },
  {
    "issueNumber": "20260515100050330",
    "number": "1",
    "color": "green",
    "premium": "1",
    "sum": 0
  },
  {
    "issueNumber": "20260515100050329",
    "number": "7",
    "color": "green",
    "premium": "7",
    "sum": 0
  },
  {
    "issueNumber": "20260515100050328",
    "number": "5",
    "color": "green,violet",
    "premium": "5",
    "sum": 0
  },
  {
    "issueNumber": "20260515100050327",
    "number": "9",
    "color": "green",
    "premium": "9",
    "sum": 0
  },
  {
    "issueNumber": "20260515100050326",
    "number": "0",
    "color": "red,violet",
    "premium": "0",
    "sum": 0
  },
  {
    "issueNumber": "20260515100050325",
    "number": "4",
    "color": "red",
    "premium": "4",
    "sum": 0
  },
  {
    "issueNumber": "20260515100050324",
    "number": "5",
    "color": "green,violet",
    "premium": "5",
    "sum": 0
  },
  {
    "issueNumber": "20260515100050323",
    "number": "3",
    "color": "green",
    "premium": "3",
    "sum": 0
  },
  {
    "issueNumber": "20260515100050322",
    "number": "7",
    "color": "green",
    "premium": "7",
    "sum": 0
  },
  {
    "issueNumber": "20260515100050321",
    "number": "1",
    "color": "green",
    "premium": "1",
    "sum": 0
  },
  {
    "issueNumber": "20260515100050320",
    "number": "6",
    "color": "red",
    "premium": "6",
    "sum": 0
  },
  {
    "issueNumber": "20260515100050319",
    "number": "1",
    "color": "green",
    "premium": "1",
    "sum": 0
  },
  {
    "issueNumber": "20260515100050318",
    "number": "6",
    "color": "red",
    "premium": "6",
    "sum": 0
  },
  {
    "issueNumber": "20260515100050317",
    "number": "8",
    "color": "red",
    "premium": "8",
    "sum": 0
  },
  {
    "issueNumber": "20260515100050316",
    "number": "1",
    "color": "green",
    "premium": "1",
    "sum": 0
  },
  {
    "issueNumber": "20260515100050315",
    "number": "4",
    "color": "red",
    "premium": "4",
    "sum": 0
  },
  {
    "issueNumber": "20260515100050314",
    "number": "5",
    "color": "green,violet",
    "premium": "5",
    "sum": 0
  },
  {
    "issueNumber": "20260515100050313",
    "number": "6",
    "color": "red",
    "premium": "6",
    "sum": 0
  },
  {
    "issueNumber": "20260515100050312",
    "number": "2",
    "color": "red",
    "premium": "2",
    "sum": 0
  },
  {
    "issueNumber": "20260515100050311",
    "number": "4",
    "color": "red",
    "premium": "4",
    "sum": 0
  },
  {
    "issueNumber": "20260515100050310",
    "number": "2",
    "color": "red",
    "premium": "2",
    "sum": 0
  },
  {
    "issueNumber": "20260515100050309",
    "number": "0",
    "color": "red,violet",
    "premium": "0",
    "sum": 0
  },
  {
    "issueNumber": "20260515100050308",
    "number": "4",
    "color": "red",
    "premium": "4",
    "sum": 0
  },
  {
    "issueNumber": "20260515100050307",
    "number": "2",
    "color": "red",
    "premium": "2",
    "sum": 0
  },
  {
    "issueNumber": "20260515100050306",
    "number": "0",
    "color": "red,violet",
    "premium": "0",
    "sum": 0
  },
  {
    "issueNumber": "20260515100050305",
    "number": "1",
    "color": "green",
    "premium": "1",
    "sum": 0
  },
  {
    "issueNumber": "20260515100050304",
    "number": "7",
    "color": "green",
    "premium": "7",
    "sum": 0
  },
  {
    "issueNumber": "20260515100050303",
    "number": "9",
    "color": "green",
    "premium": "9",
    "sum": 0
  },
  {
    "issueNumber": "20260515100050302",
    "number": "2",
    "color": "red",
    "premium": "2",
    "sum": 0
  },
  {
    "issueNumber": "20260515100050301",
    "number": "4",
    "color": "red",
    "premium": "4",
    "sum": 0
  },
  {
    "issueNumber": "20260515100050300",
    "number": "8",
    "color": "red",
    "premium": "8",
    "sum": 0
  },
  {
    "issueNumber": "20260515100050299",
    "number": "5",
    "color": "green,violet",
    "premium": "5",
    "sum": 0
  },
  {
    "issueNumber": "20260515100050298",
    "number": "2",
    "color": "red",
    "premium": "2",
    "sum": 0
  },
  {
    "issueNumber": "20260515100050297",
    "number": "1",
    "color": "green",
    "premium": "1",
    "sum": 0
  },
  {
    "issueNumber": "20260515100050296",
    "number": "4",
    "color": "red",
    "premium": "4",
    "sum": 0
  },
  {
    "issueNumber": "20260515100050295",
    "number": "0",
    "color": "red,violet",
    "premium": "0",
    "sum": 0
  },
  {
    "issueNumber": "20260515100050294",
    "number": "2",
    "color": "red",
    "premium": "2",
    "sum": 0
  },
  {
    "issueNumber": "20260515100050293",
    "number": "7",
    "color": "green",
    "premium": "7",
    "sum": 0
  },
  {
    "issueNumber": "20260515100050292",
    "number": "2",
    "color": "red",
    "premium": "2",
    "sum": 0
  },
  {
    "issueNumber": "20260515100050291",
    "number": "1",
    "color": "green",
    "premium": "1",
    "sum": 0
  },
  {
    "issueNumber": "20260515100050290",
    "number": "3",
    "color": "green",
    "premium": "3",
    "sum": 0
  },
  {
    "issueNumber": "20260515100050289",
    "number": "5",
    "color": "green,violet",
    "premium": "5",
    "sum": 0
  },
  {
    "issueNumber": "20260515100050288",
    "number": "2",
    "color": "red",
    "premium": "2",
    "sum": 0
  },
  {
    "issueNumber": "20260515100050287",
    "number": "6",
    "color": "red",
    "premium": "6",
    "sum": 0
  },
  {
    "issueNumber": "20260515100050286",
    "number": "0",
    "color": "red,violet",
    "premium": "0",
    "sum": 0
  },
  {
    "issueNumber": "20260515100050285",
    "number": "8",
    "color": "red",
    "premium": "8",
    "sum": 0
  },
  {
    "issueNumber": "20260515100050284",
    "number": "3",
    "color": "green",
    "premium": "3",
    "sum": 0
  },
  {
    "issueNumber": "20260515100050283",
    "number": "2",
    "color": "red",
    "premium": "2",
    "sum": 0
  },
  {
    "issueNumber": "20260515100050282",
    "number": "2",
    "color": "red",
    "premium": "2",
    "sum": 0
  },
  {
    "issueNumber": "20260515100050281",
    "number": "6",
    "color": "red",
    "premium": "6",
    "sum": 0
  },
  {
    "issueNumber": "20260515100050280",
    "number": "3",
    "color": "green",
    "premium": "3",
    "sum": 0
  },
  {
    "issueNumber": "20260515100050279",
    "number": "6",
    "color": "red",
    "premium": "6",
    "sum": 0
  },
  {
    "issueNumber": "20260515100050278",
    "number": "4",
    "color": "red",
    "premium": "4",
    "sum": 0
  },
  {
    "issueNumber": "20260515100050277",
    "number": "9",
    "color": "green",
    "premium": "9",
    "sum": 0
  },
  {
    "issueNumber": "20260515100050276",
    "number": "8",
    "color": "red",
    "premium": "8",
    "sum": 0
  },
  {
    "issueNumber": "20260515100050275",
    "number": "3",
    "color": "green",
    "premium": "3",
    "sum": 0
  },
  {
    "issueNumber": "20260515100050274",
    "number": "6",
    "color": "red",
    "premium": "6",
    "sum": 0
  },
  {
    "issueNumber": "20260515100050273",
    "number": "2",
    "color": "red",
    "premium": "2",
    "sum": 0
  },
  {
    "issueNumber": "20260515100050272",
    "number": "1",
    "color": "green",
    "premium": "1",
    "sum": 0
  },
  {
    "issueNumber": "20260515100050271",
    "number": "4",
    "color": "red",
    "premium": "4",
    "sum": 0
  },
  {
    "issueNumber": "20260515100050270",
    "number": "2",
    "color": "red",
    "premium": "2",
    "sum": 0
  },
  {
    "issueNumber": "20260515100050269",
    "number": "3",
    "color": "green",
    "premium": "3",
    "sum": 0
  },
  {
    "issueNumber": "20260515100050268",
    "number": "1",
    "color": "green",
    "premium": "1",
    "sum": 0
  },
  {
    "issueNumber": "20260515100050267",
    "number": "4",
    "color": "red",
    "premium": "4",
    "sum": 0
  },
  {
    "issueNumber": "20260515100050266",
    "number": "1",
    "color": "green",
    "premium": "1",
    "sum": 0
  },
  {
    "issueNumber": "20260515100050265",
    "number": "7",
    "color": "green",
    "premium": "7",
    "sum": 0
  },
  {
    "issueNumber": "20260515100050264",
    "number": "2",
    "color": "red",
    "premium": "2",
    "sum": 0
  },
  {
    "issueNumber": "20260515100050263",
    "number": "9",
    "color": "green",
    "premium": "9",
    "sum": 0
  },
  {
    "issueNumber": "20260515100050262",
    "number": "3",
    "color": "green",
    "premium": "3",
    "sum": 0
  },
  {
    "issueNumber": "20260515100050261",
    "number": "6",
    "color": "red",
    "premium": "6",
    "sum": 0
  },
  {
    "issueNumber": "20260515100050260",
    "number": "9",
    "color": "green",
    "premium": "9",
    "sum": 0
  },
  {
    "issueNumber": "20260515100050259",
    "number": "5",
    "color": "green,violet",
    "premium": "5",
    "sum": 0
  },
  {
    "issueNumber": "20260515100050258",
    "number": "8",
    "color": "red",
    "premium": "8",
    "sum": 0
  },
  {
    "issueNumber": "20260515100050257",
    "number": "7",
    "color": "green",
    "premium": "7",
    "sum": 0
  },
  {
    "issueNumber": "20260515100050256",
    "number": "0",
    "color": "red,violet",
    "premium": "0",
    "sum": 0
  },
  {
    "issueNumber": "20260515100050255",
    "number": "0",
    "color": "red,violet",
    "premium": "0",
    "sum": 0
  },
  {
    "issueNumber": "20260515100050254",
    "number": "9",
    "color": "green",
    "premium": "9",
    "sum": 0
  },
  {
    "issueNumber": "20260515100050253",
    "number": "0",
    "color": "red,violet",
    "premium": "0",
    "sum": 0
  },
  {
    "issueNumber": "20260515100050252",
    "number": "5",
    "color": "green,violet",
    "premium": "5",
    "sum": 0
  },
  {
    "issueNumber": "20260515100050251",
    "number": "9",
    "color": "green",
    "premium": "9",
    "sum": 0
  },
  {
    "issueNumber": "20260515100050250",
    "number": "7",
    "color": "green",
    "premium": "7",
    "sum": 0
  },
  {
    "issueNumber": "20260515100050249",
    "number": "2",
    "color": "red",
    "premium": "2",
    "sum": 0
  },
  {
    "issueNumber": "20260515100050248",
    "number": "7",
    "color": "green",
    "premium": "7",
    "sum": 0
  },
  {
    "issueNumber": "20260515100050247",
    "number": "8",
    "color": "red",
    "premium": "8",
    "sum": 0
  },
  {
    "issueNumber": "20260515100050246",
    "number": "3",
    "color": "green",
    "premium": "3",
    "sum": 0
  },
  {
    "issueNumber": "20260515100050245",
    "number": "6",
    "color": "red",
    "premium": "6",
    "sum": 0
  },
  {
    "issueNumber": "20260515100050244",
    "number": "8",
    "color": "red",
    "premium": "8",
    "sum": 0
  },
  {
    "issueNumber": "20260515100050243",
    "number": "1",
    "color": "green",
    "premium": "1",
    "sum": 0
  },
  {
    "issueNumber": "20260515100050242",
    "number": "7",
    "color": "green",
    "premium": "7",
    "sum": 0
  },
  {
    "issueNumber": "20260515100050241",
    "number": "0",
    "color": "red,violet",
    "premium": "0",
    "sum": 0
  },
  {
    "issueNumber": "20260515100050240",
    "number": "3",
    "color": "green",
    "premium": "3",
    "sum": 0
  },
  {
    "issueNumber": "20260515100050239",
    "number": "3",
    "color": "green",
    "premium": "3",
    "sum": 0
  },
  {
    "issueNumber": "20260515100050238",
    "number": "2",
    "color": "red",
    "premium": "2",
    "sum": 0
  },
  {
    "issueNumber": "20260515100050237",
    "number": "9",
    "color": "green",
    "premium": "9",
    "sum": 0
  },
  {
    "issueNumber": "20260515100050236",
    "number": "9",
    "color": "green",
    "premium": "9",
    "sum": 0
  },
  {
    "issueNumber": "20260515100050235",
    "number": "2",
    "color": "red",
    "premium": "2",
    "sum": 0
  },
  {
    "issueNumber": "20260515100050234",
    "number": "2",
    "color": "red",
    "premium": "2",
    "sum": 0
  },
  {
    "issueNumber": "20260515100050233",
    "number": "8",
    "color": "red",
    "premium": "8",
    "sum": 0
  },
  {
    "issueNumber": "20260515100050232",
    "number": "0",
    "color": "red,violet",
    "premium": "0",
    "sum": 0
  },
  {
    "issueNumber": "20260515100050231",
    "number": "1",
    "color": "green",
    "premium": "1",
    "sum": 0
  },
  {
    "issueNumber": "20260515100050230",
    "number": "4",
    "color": "red",
    "premium": "4",
    "sum": 0
  },
  {
    "issueNumber": "20260515100050229",
    "number": "0",
    "color": "red,violet",
    "premium": "0",
    "sum": 0
  },
  {
    "issueNumber": "20260515100050228",
    "number": "9",
    "color": "green",
    "premium": "9",
    "sum": 0
  },
  {
    "issueNumber": "20260515100050227",
    "number": "9",
    "color": "green",
    "premium": "9",
    "sum": 0
  },
  {
    "issueNumber": "20260515100050226",
    "number": "9",
    "color": "green",
    "premium": "9",
    "sum": 0
  },
  {
    "issueNumber": "20260515100050225",
    "number": "9",
    "color": "green",
    "premium": "9",
    "sum": 0
  },
  {
    "issueNumber": "20260515100050224",
    "number": "4",
    "color": "red",
    "premium": "4",
    "sum": 0
  },
  {
    "issueNumber": "20260515100050223",
    "number": "5",
    "color": "green,violet",
    "premium": "5",
    "sum": 0
  },
  {
    "issueNumber": "20260515100050222",
    "number": "3",
    "color": "green",
    "premium": "3",
    "sum": 0
  },
  {
    "issueNumber": "20260515100050221",
    "number": "8",
    "color": "red",
    "premium": "8",
    "sum": 0
  },
  {
    "issueNumber": "20260515100050220",
    "number": "5",
    "color": "green,violet",
    "premium": "5",
    "sum": 0
  },
  {
    "issueNumber": "20260515100050219",
    "number": "3",
    "color": "green",
    "premium": "3",
    "sum": 0
  },
  {
    "issueNumber": "20260515100050218",
    "number": "4",
    "color": "red",
    "premium": "4",
    "sum": 0
  },
  {
    "issueNumber": "20260515100050217",
    "number": "7",
    "color": "green",
    "premium": "7",
    "sum": 0
  },
  {
    "issueNumber": "20260515100050216",
    "number": "0",
    "color": "red,violet",
    "premium": "0",
    "sum": 0
  },
  {
    "issueNumber": "20260515100050215",
    "number": "6",
    "color": "red",
    "premium": "6",
    "sum": 0
  },
  {
    "issueNumber": "20260515100050214",
    "number": "5",
    "color": "green,violet",
    "premium": "5",
    "sum": 0
  },
  {
    "issueNumber": "20260515100050213",
    "number": "6",
    "color": "red",
    "premium": "6",
    "sum": 0
  },
  {
    "issueNumber": "20260515100050212",
    "number": "3",
    "color": "green",
    "premium": "3",
    "sum": 0
  },
  {
    "issueNumber": "20260515100050211",
    "number": "2",
    "color": "red",
    "premium": "2",
    "sum": 0
  },
  {
    "issueNumber": "20260515100050210",
    "number": "6",
    "color": "red",
    "premium": "6",
    "sum": 0
  },
  {
    "issueNumber": "20260515100050209",
    "number": "0",
    "color": "red,violet",
    "premium": "0",
    "sum": 0
  },
  {
    "issueNumber": "20260515100050208",
    "number": "6",
    "color": "red",
    "premium": "6",
    "sum": 0
  },
  {
    "issueNumber": "20260515100050207",
    "number": "2",
    "color": "red",
    "premium": "2",
    "sum": 0
  },
  {
    "issueNumber": "20260515100050206",
    "number": "5",
    "color": "green,violet",
    "premium": "5",
    "sum": 0
  },
  {
    "issueNumber": "20260515100050205",
    "number": "4",
    "color": "red",
    "premium": "4",
    "sum": 0
  },
  {
    "issueNumber": "20260515100050204",
    "number": "0",
    "color": "red,violet",
    "premium": "0",
    "sum": 0
  },
  {
    "issueNumber": "20260515100050203",
    "number": "6",
    "color": "red",
    "premium": "6",
    "sum": 0
  },
  {
    "issueNumber": "20260515100050202",
    "number": "6",
    "color": "red",
    "premium": "6",
    "sum": 0
  },
  {
    "issueNumber": "20260515100050201",
    "number": "5",
    "color": "green,violet",
    "premium": "5",
    "sum": 0
  },
  {
    "issueNumber": "20260515100050200",
    "number": "7",
    "color": "green",
    "premium": "7",
    "sum": 0
  },
  {
    "issueNumber": "20260515100050199",
    "number": "3",
    "color": "green",
    "premium": "3",
    "sum": 0
  },
  {
    "issueNumber": "20260515100050198",
    "number": "4",
    "color": "red",
    "premium": "4",
    "sum": 0
  },
  {
    "issueNumber": "20260515100050197",
    "number": "6",
    "color": "red",
    "premium": "6",
    "sum": 0
  },
  {
    "issueNumber": "20260515100050196",
    "number": "3",
    "color": "green",
    "premium": "3",
    "sum": 0
  },
  {
    "issueNumber": "20260515100050195",
    "number": "3",
    "color": "green",
    "premium": "3",
    "sum": 0
  },
  {
    "issueNumber": "20260515100050194",
    "number": "8",
    "color": "red",
    "premium": "8",
    "sum": 0
  },
  {
    "issueNumber": "20260515100050193",
    "number": "8",
    "color": "red",
    "premium": "8",
    "sum": 0
  },
  {
    "issueNumber": "20260515100050192",
    "number": "2",
    "color": "red",
    "premium": "2",
    "sum": 0
  },
  {
    "issueNumber": "20260515100050191",
    "number": "4",
    "color": "red",
    "premium": "4",
    "sum": 0
  },
  {
    "issueNumber": "20260515100050190",
    "number": "8",
    "color": "red",
    "premium": "8",
    "sum": 0
  },
  {
    "issueNumber": "20260515100050189",
    "number": "5",
    "color": "green,violet",
    "premium": "5",
    "sum": 0
  },
  {
    "issueNumber": "20260515100050188",
    "number": "8",
    "color": "red",
    "premium": "8",
    "sum": 0
  },
  {
    "issueNumber": "20260515100050187",
    "number": "7",
    "color": "green",
    "premium": "7",
    "sum": 0
  },
  {
    "issueNumber": "20260515100050186",
    "number": "3",
    "color": "green",
    "premium": "3",
    "sum": 0
  },
  {
    "issueNumber": "20260515100050185",
    "number": "0",
    "color": "red,violet",
    "premium": "0",
    "sum": 0
  },
  {
    "issueNumber": "20260515100050184",
    "number": "5",
    "color": "green,violet",
    "premium": "5",
    "sum": 0
  },
  {
    "issueNumber": "20260515100050183",
    "number": "0",
    "color": "red,violet",
    "premium": "0",
    "sum": 0
  },
  {
    "issueNumber": "20260515100050182",
    "number": "6",
    "color": "red",
    "premium": "6",
    "sum": 0
  },
  {
    "issueNumber": "20260515100050181",
    "number": "0",
    "color": "red,violet",
    "premium": "0",
    "sum": 0
  },
  {
    "issueNumber": "20260515100050180",
    "number": "7",
    "color": "green",
    "premium": "7",
    "sum": 0
  },
  {
    "issueNumber": "20260515100050179",
    "number": "5",
    "color": "green,violet",
    "premium": "5",
    "sum": 0
  },
  {
    "issueNumber": "20260515100050178",
    "number": "8",
    "color": "red",
    "premium": "8",
    "sum": 0
  },
  {
    "issueNumber": "20260515100050177",
    "number": "2",
    "color": "red",
    "premium": "2",
    "sum": 0
  },
  {
    "issueNumber": "20260515100050176",
    "number": "8",
    "color": "red",
    "premium": "8",
    "sum": 0
  },
  {
    "issueNumber": "20260515100050175",
    "number": "9",
    "color": "green",
    "premium": "9",
    "sum": 0
  },
  {
    "issueNumber": "20260515100050174",
    "number": "3",
    "color": "green",
    "premium": "3",
    "sum": 0
  },
  {
    "issueNumber": "20260515100050173",
    "number": "9",
    "color": "green",
    "premium": "9",
    "sum": 0
  },
  {
    "issueNumber": "20260515100050172",
    "number": "6",
    "color": "red",
    "premium": "6",
    "sum": 0
  },
  {
    "issueNumber": "20260515100050171",
    "number": "0",
    "color": "red,violet",
    "premium": "0",
    "sum": 0
  },
  {
    "issueNumber": "20260515100050170",
    "number": "2",
    "color": "red",
    "premium": "2",
    "sum": 0
  },
  {
    "issueNumber": "20260515100050169",
    "number": "0",
    "color": "red,violet",
    "premium": "0",
    "sum": 0
  },
  {
    "issueNumber": "20260515100050168",
    "number": "3",
    "color": "green",
    "premium": "3",
    "sum": 0
  },
  {
    "issueNumber": "20260515100050167",
    "number": "1",
    "color": "green",
    "premium": "1",
    "sum": 0
  },
  {
    "issueNumber": "20260515100050166",
    "number": "4",
    "color": "red",
    "premium": "4",
    "sum": 0
  },
  {
    "issueNumber": "20260515100050165",
    "number": "9",
    "color": "green",
    "premium": "9",
    "sum": 0
  },
  {
    "issueNumber": "20260515100050164",
    "number": "4",
    "color": "red",
    "premium": "4",
    "sum": 0
  },
  {
    "issueNumber": "20260515100050163",
    "number": "6",
    "color": "red",
    "premium": "6",
    "sum": 0
  },
  {
    "issueNumber": "20260515100050162",
    "number": "9",
    "color": "green",
    "premium": "9",
    "sum": 0
  },
  {
    "issueNumber": "20260515100050161",
    "number": "4",
    "color": "red",
    "premium": "4",
    "sum": 0
  },
  {
    "issueNumber": "20260515100050160",
    "number": "8",
    "color": "red",
    "premium": "8",
    "sum": 0
  },
  {
    "issueNumber": "20260515100050159",
    "number": "6",
    "color": "red",
    "premium": "6",
    "sum": 0
  },
  {
    "issueNumber": "20260515100050158",
    "number": "2",
    "color": "red",
    "premium": "2",
    "sum": 0
  },
  {
    "issueNumber": "20260515100050157",
    "number": "6",
    "color": "red",
    "premium": "6",
    "sum": 0
  },
  {
    "issueNumber": "20260515100050156",
    "number": "5",
    "color": "green,violet",
    "premium": "5",
    "sum": 0
  },
  {
    "issueNumber": "20260515100050155",
    "number": "1",
    "color": "green",
    "premium": "1",
    "sum": 0
  },
  {
    "issueNumber": "20260515100050154",
    "number": "4",
    "color": "red",
    "premium": "4",
    "sum": 0
  },
  {
    "issueNumber": "20260515100050153",
    "number": "6",
    "color": "red",
    "premium": "6",
    "sum": 0
  },
  {
    "issueNumber": "20260515100050152",
    "number": "1",
    "color": "green",
    "premium": "1",
    "sum": 0
  },
  {
    "issueNumber": "20260515100050151",
    "number": "8",
    "color": "red",
    "premium": "8",
    "sum": 0
  },
  {
    "issueNumber": "20260515100050150",
    "number": "3",
    "color": "green",
    "premium": "3",
    "sum": 0
  },
  {
    "issueNumber": "20260515100050149",
    "number": "4",
    "color": "red",
    "premium": "4",
    "sum": 0
  },
  {
    "issueNumber": "20260515100050148",
    "number": "5",
    "color": "green,violet",
    "premium": "5",
    "sum": 0
  },
  {
    "issueNumber": "20260515100050147",
    "number": "9",
    "color": "green",
    "premium": "9",
    "sum": 0
  },
  {
    "issueNumber": "20260515100050146",
    "number": "0",
    "color": "red,violet",
    "premium": "0",
    "sum": 0
  },
  {
    "issueNumber": "20260515100050145",
    "number": "0",
    "color": "red,violet",
    "premium": "0",
    "sum": 0
  },
  {
    "issueNumber": "20260515100050144",
    "number": "0",
    "color": "red,violet",
    "premium": "0",
    "sum": 0
  },
  {
    "issueNumber": "20260515100050143",
    "number": "4",
    "color": "red",
    "premium": "4",
    "sum": 0
  },
  {
    "issueNumber": "20260515100050142",
    "number": "3",
    "color": "green",
    "premium": "3",
    "sum": 0
  },
  {
    "issueNumber": "20260515100050141",
    "number": "6",
    "color": "red",
    "premium": "6",
    "sum": 0
  },
  {
    "issueNumber": "20260515100050140",
    "number": "6",
    "color": "red",
    "premium": "6",
    "sum": 0
  },
  {
    "issueNumber": "20260515100050139",
    "number": "1",
    "color": "green",
    "premium": "1",
    "sum": 0
  },
  {
    "issueNumber": "20260515100050138",
    "number": "6",
    "color": "red",
    "premium": "6",
    "sum": 0
  },
  {
    "issueNumber": "20260515100050137",
    "number": "1",
    "color": "green",
    "premium": "1",
    "sum": 0
  },
  {
    "issueNumber": "20260515100050136",
    "number": "4",
    "color": "red",
    "premium": "4",
    "sum": 0
  },
  {
    "issueNumber": "20260515100050135",
    "number": "3",
    "color": "green",
    "premium": "3",
    "sum": 0
  },
  {
    "issueNumber": "20260515100050134",
    "number": "3",
    "color": "green",
    "premium": "3",
    "sum": 0
  },
  {
    "issueNumber": "20260515100050133",
    "number": "6",
    "color": "red",
    "premium": "6",
    "sum": 0
  },
  {
    "issueNumber": "20260515100050132",
    "number": "0",
    "color": "red,violet",
    "premium": "0",
    "sum": 0
  },
  {
    "issueNumber": "20260515100050131",
    "number": "9",
    "color": "green",
    "premium": "9",
    "sum": 0
  },
  {
    "issueNumber": "20260515100050130",
    "number": "4",
    "color": "red",
    "premium": "4",
    "sum": 0
  },
  {
    "issueNumber": "20260515100050129",
    "number": "8",
    "color": "red",
    "premium": "8",
    "sum": 0
  },
  {
    "issueNumber": "20260515100050128",
    "number": "9",
    "color": "green",
    "premium": "9",
    "sum": 0
  },
  {
    "issueNumber": "20260515100050127",
    "number": "9",
    "color": "green",
    "premium": "9",
    "sum": 0
  },
  {
    "issueNumber": "20260515100050126",
    "number": "4",
    "color": "red",
    "premium": "4",
    "sum": 0
  },
  {
    "issueNumber": "20260515100050125",
    "number": "5",
    "color": "green,violet",
    "premium": "5",
    "sum": 0
  },
  {
    "issueNumber": "20260515100050124",
    "number": "2",
    "color": "red",
    "premium": "2",
    "sum": 0
  },
  {
    "issueNumber": "20260515100050123",
    "number": "0",
    "color": "red,violet",
    "premium": "0",
    "sum": 0
  },
  {
    "issueNumber": "20260515100050122",
    "number": "2",
    "color": "red",
    "premium": "2",
    "sum": 0
  },
  {
    "issueNumber": "20260515100050121",
    "number": "1",
    "color": "green",
    "premium": "1",
    "sum": 0
  },
  {
    "issueNumber": "20260515100050120",
    "number": "4",
    "color": "red",
    "premium": "4",
    "sum": 0
  },
  {
    "issueNumber": "20260515100050119",
    "number": "6",
    "color": "red",
    "premium": "6",
    "sum": 0
  },
  {
    "issueNumber": "20260515100050118",
    "number": "2",
    "color": "red",
    "premium": "2",
    "sum": 0
  },
  {
    "issueNumber": "20260515100050117",
    "number": "1",
    "color": "green",
    "premium": "1",
    "sum": 0
  },
  {
    "issueNumber": "20260515100050116",
    "number": "3",
    "color": "green",
    "premium": "3",
    "sum": 0
  },
  {
    "issueNumber": "20260515100050115",
    "number": "4",
    "color": "red",
    "premium": "4",
    "sum": 0
  },
  {
    "issueNumber": "20260515100050114",
    "number": "6",
    "color": "red",
    "premium": "6",
    "sum": 0
  },
  {
    "issueNumber": "20260515100050113",
    "number": "6",
    "color": "red",
    "premium": "6",
    "sum": 0
  },
  {
    "issueNumber": "20260515100050112",
    "number": "5",
    "color": "green,violet",
    "premium": "5",
    "sum": 0
  },
  {
    "issueNumber": "20260515100050111",
    "number": "6",
    "color": "red",
    "premium": "6",
    "sum": 0
  },
  {
    "issueNumber": "20260515100050110",
    "number": "1",
    "color": "green",
    "premium": "1",
    "sum": 0
  },
  {
    "issueNumber": "20260515100050109",
    "number": "1",
    "color": "green",
    "premium": "1",
    "sum": 0
  },
  {
    "issueNumber": "20260515100050108",
    "number": "5",
    "color": "green,violet",
    "premium": "5",
    "sum": 0
  },
  {
    "issueNumber": "20260515100050107",
    "number": "7",
    "color": "green",
    "premium": "7",
    "sum": 0
  },
  {
    "issueNumber": "20260515100050106",
    "number": "5",
    "color": "green,violet",
    "premium": "5",
    "sum": 0
  },
  {
    "issueNumber": "20260515100050105",
    "number": "2",
    "color": "red",
    "premium": "2",
    "sum": 0
  },
  {
    "issueNumber": "20260515100050104",
    "number": "2",
    "color": "red",
    "premium": "2",
    "sum": 0
  },
  {
    "issueNumber": "20260515100050103",
    "number": "7",
    "color": "green",
    "premium": "7",
    "sum": 0
  },
  {
    "issueNumber": "20260515100050102",
    "number": "7",
    "color": "green",
    "premium": "7",
    "sum": 0
  },
  {
    "issueNumber": "20260515100050101",
    "number": "0",
    "color": "red,violet",
    "premium": "0",
    "sum": 0
  },
  {
    "issueNumber": "20260515100050100",
    "number": "2",
    "color": "red",
    "premium": "2",
    "sum": 0
  },
  {
    "issueNumber": "20260515100050099",
    "number": "5",
    "color": "green,violet",
    "premium": "5",
    "sum": 0
  },
  {
    "issueNumber": "20260515100050098",
    "number": "4",
    "color": "red",
    "premium": "4",
    "sum": 0
  },
  {
    "issueNumber": "20260515100050097",
    "number": "8",
    "color": "red",
    "premium": "8",
    "sum": 0
  },
  {
    "issueNumber": "20260515100050096",
    "number": "5",
    "color": "green,violet",
    "premium": "5",
    "sum": 0
  },
  {
    "issueNumber": "20260515100050095",
    "number": "1",
    "color": "green",
    "premium": "1",
    "sum": 0
  },
  {
    "issueNumber": "20260515100050094",
    "number": "3",
    "color": "green",
    "premium": "3",
    "sum": 0
  },
  {
    "issueNumber": "20260515100050093",
    "number": "7",
    "color": "green",
    "premium": "7",
    "sum": 0
  },
  {
    "issueNumber": "20260515100050092",
    "number": "3",
    "color": "green",
    "premium": "3",
    "sum": 0
  },
  {
    "issueNumber": "20260515100050091",
    "number": "0",
    "color": "red,violet",
    "premium": "0",
    "sum": 0
  },
  {
    "issueNumber": "20260515100050090",
    "number": "5",
    "color": "green,violet",
    "premium": "5",
    "sum": 0
  },
  {
    "issueNumber": "20260515100050089",
    "number": "7",
    "color": "green",
    "premium": "7",
    "sum": 0
  },
  {
    "issueNumber": "20260515100050088",
    "number": "6",
    "color": "red",
    "premium": "6",
    "sum": 0
  },
  {
    "issueNumber": "20260515100050087",
    "number": "8",
    "color": "red",
    "premium": "8",
    "sum": 0
  },
  {
    "issueNumber": "20260515100050086",
    "number": "7",
    "color": "green",
    "premium": "7",
    "sum": 0
  },
  {
    "issueNumber": "20260515100050085",
    "number": "5",
    "color": "green,violet",
    "premium": "5",
    "sum": 0
  },
  {
    "issueNumber": "20260515100050084",
    "number": "7",
    "color": "green",
    "premium": "7",
    "sum": 0
  },
  {
    "issueNumber": "20260515100050083",
    "number": "9",
    "color": "green",
    "premium": "9",
    "sum": 0
  },
  {
    "issueNumber": "20260515100050082",
    "number": "4",
    "color": "red",
    "premium": "4",
    "sum": 0
  },
  {
    "issueNumber": "20260515100050081",
    "number": "4",
    "color": "red",
    "premium": "4",
    "sum": 0
  },
  {
    "issueNumber": "20260515100050080",
    "number": "6",
    "color": "red",
    "premium": "6",
    "sum": 0
  },
  {
    "issueNumber": "20260515100050079",
    "number": "5",
    "color": "green,violet",
    "premium": "5",
    "sum": 0
  },
  {
    "issueNumber": "20260515100050078",
    "number": "4",
    "color": "red",
    "premium": "4",
    "sum": 0
  },
  {
    "issueNumber": "20260515100050077",
    "number": "8",
    "color": "red",
    "premium": "8",
    "sum": 0
  },
  {
    "issueNumber": "20260515100050076",
    "number": "0",
    "color": "red,violet",
    "premium": "0",
    "sum": 0
  },
  {
    "issueNumber": "20260515100050075",
    "number": "2",
    "color": "red",
    "premium": "2",
    "sum": 0
  },
  {
    "issueNumber": "20260515100050074",
    "number": "5",
    "color": "green,violet",
    "premium": "5",
    "sum": 0
  },
  {
    "issueNumber": "20260515100050073",
    "number": "9",
    "color": "green",
    "premium": "9",
    "sum": 0
  },
  {
    "issueNumber": "20260515100050072",
    "number": "3",
    "color": "green",
    "premium": "3",
    "sum": 0
  },
  {
    "issueNumber": "20260515100050071",
    "number": "7",
    "color": "green",
    "premium": "7",
    "sum": 0
  },
  {
    "issueNumber": "20260515100050070",
    "number": "3",
    "color": "green",
    "premium": "3",
    "sum": 0
  },
  {
    "issueNumber": "20260515100050069",
    "number": "0",
    "color": "red,violet",
    "premium": "0",
    "sum": 0
  },
  {
    "issueNumber": "20260515100050068",
    "number": "6",
    "color": "red",
    "premium": "6",
    "sum": 0
  },
  {
    "issueNumber": "20260515100050067",
    "number": "4",
    "color": "red",
    "premium": "4",
    "sum": 0
  },
  {
    "issueNumber": "20260515100050066",
    "number": "5",
    "color": "green,violet",
    "premium": "5",
    "sum": 0
  },
  {
    "issueNumber": "20260515100050065",
    "number": "8",
    "color": "red",
    "premium": "8",
    "sum": 0
  },
  {
    "issueNumber": "20260515100050064",
    "number": "0",
    "color": "red,violet",
    "premium": "0",
    "sum": 0
  },
  {
    "issueNumber": "20260515100050063",
    "number": "3",
    "color": "green",
    "premium": "3",
    "sum": 0
  },
  {
    "issueNumber": "20260515100050062",
    "number": "5",
    "color": "green,violet",
    "premium": "5",
    "sum": 0
  },
  {
    "issueNumber": "20260515100050061",
    "number": "5",
    "color": "green,violet",
    "premium": "5",
    "sum": 0
  },
  {
    "issueNumber": "20260515100050060",
    "number": "3",
    "color": "green",
    "premium": "3",
    "sum": 0
  },
  {
    "issueNumber": "20260515100050059",
    "number": "6",
    "color": "red",
    "premium": "6",
    "sum": 0
  },
  {
    "issueNumber": "20260515100050058",
    "number": "9",
    "color": "green",
    "premium": "9",
    "sum": 0
  },
  {
    "issueNumber": "20260515100050057",
    "number": "4",
    "color": "red",
    "premium": "4",
    "sum": 0
  },
  {
    "issueNumber": "20260515100050056",
    "number": "3",
    "color": "green",
    "premium": "3",
    "sum": 0
  },
  {
    "issueNumber": "20260515100050055",
    "number": "8",
    "color": "red",
    "premium": "8",
    "sum": 0
  }
]