[
  {
    "issueNumber": "20260209100050942",
    "number": "3",
    "color": "green",
    "premium": "3",
    "sum": 0
  },
  {
    "issueNumber": "20260209100050941",
    "number": "0",
    "color": "red,violet",
    "premium": "0",
    "sum": 0
  },
  {
    "issueNumber": "20260209100050940",
    "number": "4",
    "color": "red",
    "premium": "4",
    "sum": 0
  },
  {
    "issueNumber": "20260209100050939",
    "number": "0",
    "color": "red,violet",
    "premium": "0",
    "sum": 0
  },
  {
    "issueNumber": "20260209100050938",
    "number": "8",
    "color": "red",
    "premium": "8",
    "sum": 0
  },
  {
    "issueNumber": "20260209100050937",
    "number": "8",
    "color": "red",
    "premium": "8",
    "sum": 0
  },
  {
    "issueNumber": "20260209100050936",
    "number": "8",
    "color": "red",
    "premium": "8",
    "sum": 0
  },
  {
    "issueNumber": "20260209100050935",
    "number": "8",
    "color": "red",
    "premium": "8",
    "sum": 0
  },
  {
    "issueNumber": "20260209100050934",
    "number": "2",
    "color": "red",
    "premium": "2",
    "sum": 0
  },
  {
    "issueNumber": "20260209100050933",
    "number": "8",
    "color": "red",
    "premium": "8",
    "sum": 0
  },
  {
    "issueNumber": "20260209100050932",
    "number": "6",
    "color": "red",
    "premium": "6",
    "sum": 0
  },
  {
    "issueNumber": "20260209100050931",
    "number": "2",
    "color": "red",
    "premium": "2",
    "sum": 0
  },
  {
    "issueNumber": "20260209100050930",
    "number": "6",
    "color": "red",
    "premium": "6",
    "sum": 0
  },
  {
    "issueNumber": "20260209100050929",
    "number": "4",
    "color": "red",
    "premium": "4",
    "sum": 0
  },
  {
    "issueNumber": "20260209100050928",
    "number": "1",
    "color": "green",
    "premium": "1",
    "sum": 0
  },
  {
    "issueNumber": "20260209100050927",
    "number": "0",
    "color": "red,violet",
    "premium": "0",
    "sum": 0
  },
  {
    "issueNumber": "20260209100050926",
    "number": "5",
    "color": "green,violet",
    "premium": "5",
    "sum": 0
  },
  {
    "issueNumber": "20260209100050925",
    "number": "0",
    "color": "red,violet",
    "premium": "0",
    "sum": 0
  },
  {
    "issueNumber": "20260209100050924",
    "number": "6",
    "color": "red",
    "premium": "6",
    "sum": 0
  },
  {
    "issueNumber": "20260209100050923",
    "number": "5",
    "color": "green,violet",
    "premium": "5",
    "sum": 0
  },
  {
    "issueNumber": "20260209100050922",
    "number": "4",
    "color": "red",
    "premium": "4",
    "sum": 0
  },
  {
    "issueNumber": "20260209100050921",
    "number": "0",
    "color": "red,violet",
    "premium": "0",
    "sum": 0
  },
  {
    "issueNumber": "20260209100050920",
    "number": "6",
    "color": "red",
    "premium": "6",
    "sum": 0
  },
  {
    "issueNumber": "20260209100050919",
    "number": "9",
    "color": "green",
    "premium": "9",
    "sum": 0
  },
  {
    "issueNumber": "20260209100050918",
    "number": "6",
    "color": "red",
    "premium": "6",
    "sum": 0
  },
  {
    "issueNumber": "20260209100050917",
    "number": "0",
    "color": "red,violet",
    "premium": "0",
    "sum": 0
  },
  {
    "issueNumber": "20260209100050916",
    "number": "0",
    "color": "red,violet",
    "premium": "0",
    "sum": 0
  },
  {
    "issueNumber": "20260209100050915",
    "number": "1",
    "color": "green",
    "premium": "1",
    "sum": 0
  },
  {
    "issueNumber": "20260209100050914",
    "number": "8",
    "color": "red",
    "premium": "8",
    "sum": 0
  },
  {
    "issueNumber": "20260209100050913",
    "number": "2",
    "color": "red",
    "premium": "2",
    "sum": 0
  },
  {
    "issueNumber": "20260209100050912",
    "number": "9",
    "color": "green",
    "premium": "9",
    "sum": 0
  },
  {
    "issueNumber": "20260209100050911",
    "number": "7",
    "color": "green",
    "premium": "7",
    "sum": 0
  },
  {
    "issueNumber": "20260209100050910",
    "number": "9",
    "color": "green",
    "premium": "9",
    "sum": 0
  },
  {
    "issueNumber": "20260209100050909",
    "number": "3",
    "color": "green",
    "premium": "3",
    "sum": 0
  },
  {
    "issueNumber": "20260209100050908",
    "number": "8",
    "color": "red",
    "premium": "8",
    "sum": 0
  },
  {
    "issueNumber": "20260209100050907",
    "number": "9",
    "color": "green",
    "premium": "9",
    "sum": 0
  },
  {
    "issueNumber": "20260209100050906",
    "number": "9",
    "color": "green",
    "premium": "9",
    "sum": 0
  },
  {
    "issueNumber": "20260209100050905",
    "number": "8",
    "color": "red",
    "premium": "8",
    "sum": 0
  },
  {
    "issueNumber": "20260209100050904",
    "number": "4",
    "color": "red",
    "premium": "4",
    "sum": 0
  },
  {
    "issueNumber": "20260209100050903",
    "number": "3",
    "color": "green",
    "premium": "3",
    "sum": 0
  },
  {
    "issueNumber": "20260209100050902",
    "number": "7",
    "color": "green",
    "premium": "7",
    "sum": 0
  },
  {
    "issueNumber": "20260209100050901",
    "number": "1",
    "color": "green",
    "premium": "1",
    "sum": 0
  },
  {
    "issueNumber": "20260209100050900",
    "number": "0",
    "color": "red,violet",
    "premium": "0",
    "sum": 0
  },
  {
    "issueNumber": "20260209100050899",
    "number": "0",
    "color": "red,violet",
    "premium": "0",
    "sum": 0
  },
  {
    "issueNumber": "20260209100050898",
    "number": "5",
    "color": "green,violet",
    "premium": "5",
    "sum": 0
  },
  {
    "issueNumber": "20260209100050897",
    "number": "9",
    "color": "green",
    "premium": "9",
    "sum": 0
  },
  {
    "issueNumber": "20260209100050896",
    "number": "7",
    "color": "green",
    "premium": "7",
    "sum": 0
  },
  {
    "issueNumber": "20260209100050895",
    "number": "1",
    "color": "green",
    "premium": "1",
    "sum": 0
  },
  {
    "issueNumber": "20260209100050894",
    "number": "9",
    "color": "green",
    "premium": "9",
    "sum": 0
  },
  {
    "issueNumber": "20260209100050893",
    "number": "7",
    "color": "green",
    "premium": "7",
    "sum": 0
  },
  {
    "issueNumber": "20260209100050892",
    "number": "4",
    "color": "red",
    "premium": "4",
    "sum": 0
  },
  {
    "issueNumber": "20260209100050891",
    "number": "5",
    "color": "green,violet",
    "premium": "5",
    "sum": 0
  },
  {
    "issueNumber": "20260209100050890",
    "number": "5",
    "color": "green,violet",
    "premium": "5",
    "sum": 0
  },
  {
    "issueNumber": "20260209100050889",
    "number": "0",
    "color": "red,violet",
    "premium": "0",
    "sum": 0
  },
  {
    "issueNumber": "20260209100050888",
    "number": "6",
    "color": "red",
    "premium": "6",
    "sum": 0
  },
  {
    "issueNumber": "20260209100050887",
    "number": "3",
    "color": "green",
    "premium": "3",
    "sum": 0
  },
  {
    "issueNumber": "20260209100050886",
    "number": "7",
    "color": "green",
    "premium": "7",
    "sum": 0
  },
  {
    "issueNumber": "20260209100050885",
    "number": "7",
    "color": "green",
    "premium": "7",
    "sum": 0
  },
  {
    "issueNumber": "20260209100050884",
    "number": "5",
    "color": "green,violet",
    "premium": "5",
    "sum": 0
  },
  {
    "issueNumber": "20260209100050883",
    "number": "2",
    "color": "red",
    "premium": "2",
    "sum": 0
  },
  {
    "issueNumber": "20260209100050882",
    "number": "3",
    "color": "green",
    "premium": "3",
    "sum": 0
  },
  {
    "issueNumber": "20260209100050881",
    "number": "0",
    "color": "red,violet",
    "premium": "0",
    "sum": 0
  },
  {
    "issueNumber": "20260209100050880",
    "number": "8",
    "color": "red",
    "premium": "8",
    "sum": 0
  },
  {
    "issueNumber": "20260209100050879",
    "number": "0",
    "color": "red,violet",
    "premium": "0",
    "sum": 0
  },
  {
    "issueNumber": "20260209100050878",
    "number": "1",
    "color": "green",
    "premium": "1",
    "sum": 0
  },
  {
    "issueNumber": "20260209100050877",
    "number": "5",
    "color": "green,violet",
    "premium": "5",
    "sum": 0
  },
  {
    "issueNumber": "20260209100050876",
    "number": "2",
    "color": "red",
    "premium": "2",
    "sum": 0
  },
  {
    "issueNumber": "20260209100050875",
    "number": "7",
    "color": "green",
    "premium": "7",
    "sum": 0
  },
  {
    "issueNumber": "20260209100050874",
    "number": "9",
    "color": "green",
    "premium": "9",
    "sum": 0
  },
  {
    "issueNumber": "20260209100050873",
    "number": "1",
    "color": "green",
    "premium": "1",
    "sum": 0
  },
  {
    "issueNumber": "20260209100050872",
    "number": "8",
    "color": "red",
    "premium": "8",
    "sum": 0
  },
  {
    "issueNumber": "20260209100050871",
    "number": "5",
    "color": "green,violet",
    "premium": "5",
    "sum": 0
  },
  {
    "issueNumber": "20260209100050870",
    "number": "2",
    "color": "red",
    "premium": "2",
    "sum": 0
  },
  {
    "issueNumber": "20260209100050869",
    "number": "5",
    "color": "green,violet",
    "premium": "5",
    "sum": 0
  },
  {
    "issueNumber": "20260209100050868",
    "number": "2",
    "color": "red",
    "premium": "2",
    "sum": 0
  },
  {
    "issueNumber": "20260209100050867",
    "number": "9",
    "color": "green",
    "premium": "9",
    "sum": 0
  },
  {
    "issueNumber": "20260209100050866",
    "number": "3",
    "color": "green",
    "premium": "3",
    "sum": 0
  },
  {
    "issueNumber": "20260209100050865",
    "number": "1",
    "color": "green",
    "premium": "1",
    "sum": 0
  },
  {
    "issueNumber": "20260209100050864",
    "number": "5",
    "color": "green,violet",
    "premium": "5",
    "sum": 0
  },
  {
    "issueNumber": "20260209100050863",
    "number": "5",
    "color": "green,violet",
    "premium": "5",
    "sum": 0
  },
  {
    "issueNumber": "20260209100050862",
    "number": "2",
    "color": "red",
    "premium": "2",
    "sum": 0
  },
  {
    "issueNumber": "20260209100050861",
    "number": "0",
    "color": "red,violet",
    "premium": "0",
    "sum": 0
  },
  {
    "issueNumber": "20260209100050860",
    "number": "7",
    "color": "green",
    "premium": "7",
    "sum": 0
  },
  {
    "issueNumber": "20260209100050859",
    "number": "5",
    "color": "green,violet",
    "premium": "5",
    "sum": 0
  },
  {
    "issueNumber": "20260209100050858",
    "number": "2",
    "color": "red",
    "premium": "2",
    "sum": 0
  },
  {
    "issueNumber": "20260209100050857",
    "number": "1",
    "color": "green",
    "premium": "1",
    "sum": 0
  },
  {
    "issueNumber": "20260209100050856",
    "number": "3",
    "color": "green",
    "premium": "3",
    "sum": 0
  },
  {
    "issueNumber": "20260209100050855",
    "number": "8",
    "color": "red",
    "premium": "8",
    "sum": 0
  },
  {
    "issueNumber": "20260209100050854",
    "number": "5",
    "color": "green,violet",
    "premium": "5",
    "sum": 0
  },
  {
    "issueNumber": "20260209100050853",
    "number": "0",
    "color": "red,violet",
    "premium": "0",
    "sum": 0
  },
  {
    "issueNumber": "20260209100050852",
    "number": "3",
    "color": "green",
    "premium": "3",
    "sum": 0
  },
  {
    "issueNumber": "20260209100050851",
    "number": "6",
    "color": "red",
    "premium": "6",
    "sum": 0
  },
  {
    "issueNumber": "20260209100050850",
    "number": "5",
    "color": "green,violet",
    "premium": "5",
    "sum": 0
  },
  {
    "issueNumber": "20260209100050849",
    "number": "6",
    "color": "red",
    "premium": "6",
    "sum": 0
  },
  {
    "issueNumber": "20260209100050848",
    "number": "5",
    "color": "green,violet",
    "premium": "5",
    "sum": 0
  },
  {
    "issueNumber": "20260209100050847",
    "number": "4",
    "color": "red",
    "premium": "4",
    "sum": 0
  },
  {
    "issueNumber": "20260209100050846",
    "number": "7",
    "color": "green",
    "premium": "7",
    "sum": 0
  },
  {
    "issueNumber": "20260209100050845",
    "number": "3",
    "color": "green",
    "premium": "3",
    "sum": 0
  },
  {
    "issueNumber": "20260209100050844",
    "number": "4",
    "color": "red",
    "premium": "4",
    "sum": 0
  },
  {
    "issueNumber": "20260209100050843",
    "number": "4",
    "color": "red",
    "premium": "4",
    "sum": 0
  },
  {
    "issueNumber": "20260209100050842",
    "number": "7",
    "color": "green",
    "premium": "7",
    "sum": 0
  },
  {
    "issueNumber": "20260209100050841",
    "number": "1",
    "color": "green",
    "premium": "1",
    "sum": 0
  },
  {
    "issueNumber": "20260209100050840",
    "number": "9",
    "color": "green",
    "premium": "9",
    "sum": 0
  },
  {
    "issueNumber": "20260209100050839",
    "number": "1",
    "color": "green",
    "premium": "1",
    "sum": 0
  },
  {
    "issueNumber": "20260209100050838",
    "number": "2",
    "color": "red",
    "premium": "2",
    "sum": 0
  },
  {
    "issueNumber": "20260209100050837",
    "number": "2",
    "color": "red",
    "premium": "2",
    "sum": 0
  },
  {
    "issueNumber": "20260209100050836",
    "number": "5",
    "color": "green,violet",
    "premium": "5",
    "sum": 0
  },
  {
    "issueNumber": "20260209100050835",
    "number": "0",
    "color": "red,violet",
    "premium": "0",
    "sum": 0
  },
  {
    "issueNumber": "20260209100050834",
    "number": "4",
    "color": "red",
    "premium": "4",
    "sum": 0
  },
  {
    "issueNumber": "20260209100050833",
    "number": "1",
    "color": "green",
    "premium": "1",
    "sum": 0
  },
  {
    "issueNumber": "20260209100050832",
    "number": "7",
    "color": "green",
    "premium": "7",
    "sum": 0
  },
  {
    "issueNumber": "20260209100050831",
    "number": "5",
    "color": "green,violet",
    "premium": "5",
    "sum": 0
  },
  {
    "issueNumber": "20260209100050830",
    "number": "8",
    "color": "red",
    "premium": "8",
    "sum": 0
  },
  {
    "issueNumber": "20260209100050829",
    "number": "7",
    "color": "green",
    "premium": "7",
    "sum": 0
  },
  {
    "issueNumber": "20260209100050828",
    "number": "8",
    "color": "red",
    "premium": "8",
    "sum": 0
  },
  {
    "issueNumber": "20260209100050827",
    "number": "8",
    "color": "red",
    "premium": "8",
    "sum": 0
  },
  {
    "issueNumber": "20260209100050826",
    "number": "9",
    "color": "green",
    "premium": "9",
    "sum": 0
  },
  {
    "issueNumber": "20260209100050825",
    "number": "8",
    "color": "red",
    "premium": "8",
    "sum": 0
  },
  {
    "issueNumber": "20260209100050824",
    "number": "1",
    "color": "green",
    "premium": "1",
    "sum": 0
  },
  {
    "issueNumber": "20260209100050823",
    "number": "1",
    "color": "green",
    "premium": "1",
    "sum": 0
  },
  {
    "issueNumber": "20260209100050822",
    "number": "3",
    "color": "green",
    "premium": "3",
    "sum": 0
  },
  {
    "issueNumber": "20260209100050821",
    "number": "9",
    "color": "green",
    "premium": "9",
    "sum": 0
  },
  {
    "issueNumber": "20260209100050820",
    "number": "6",
    "color": "red",
    "premium": "6",
    "sum": 0
  },
  {
    "issueNumber": "20260209100050819",
    "number": "2",
    "color": "red",
    "premium": "2",
    "sum": 0
  },
  {
    "issueNumber": "20260209100050818",
    "number": "4",
    "color": "red",
    "premium": "4",
    "sum": 0
  },
  {
    "issueNumber": "20260209100050817",
    "number": "6",
    "color": "red",
    "premium": "6",
    "sum": 0
  },
  {
    "issueNumber": "20260209100050816",
    "number": "5",
    "color": "green,violet",
    "premium": "5",
    "sum": 0
  },
  {
    "issueNumber": "20260209100050815",
    "number": "5",
    "color": "green,violet",
    "premium": "5",
    "sum": 0
  },
  {
    "issueNumber": "20260209100050814",
    "number": "0",
    "color": "red,violet",
    "premium": "0",
    "sum": 0
  },
  {
    "issueNumber": "20260209100050813",
    "number": "3",
    "color": "green",
    "premium": "3",
    "sum": 0
  },
  {
    "issueNumber": "20260209100050812",
    "number": "8",
    "color": "red",
    "premium": "8",
    "sum": 0
  },
  {
    "issueNumber": "20260209100050811",
    "number": "1",
    "color": "green",
    "premium": "1",
    "sum": 0
  },
  {
    "issueNumber": "20260209100050810",
    "number": "2",
    "color": "red",
    "premium": "2",
    "sum": 0
  },
  {
    "issueNumber": "20260209100050809",
    "number": "9",
    "color": "green",
    "premium": "9",
    "sum": 0
  },
  {
    "issueNumber": "20260209100050808",
    "number": "8",
    "color": "red",
    "premium": "8",
    "sum": 0
  },
  {
    "issueNumber": "20260209100050807",
    "number": "7",
    "color": "green",
    "premium": "7",
    "sum": 0
  }
]